archive_ops/CleanCurrent.py
archive_ops/DeepArchive.py
archive_ops/DeepArchiveParser.py
archive_ops/DeepArchiveSingleZip.py
archive_ops/DipLog.py
archive_ops/DipLogParser.py
archive_ops/GetReadyWorksForStates.py
archive_ops/InvertWork.py
archive_ops/InvertWorkException.py
archive_ops/Resolvers.py
archive_ops/SaveWorkFacts.py
archive_ops/TestGetReadyWorksForStates.py
archive_ops/__init__.py
archive_ops/api.py
archive_ops/locators.py
archive_ops/shell_ws.py
archive_ops/models/__init__.py
archive_ops/models/drsmodel.py
archive_ops/models/drsmodelSqlA20.py
migrate_works/ArchiveMigrator.py
migrate_works/MigrateLocks.py
migrate_works/__init__.py
migrate_works/measure_archive_fixity.py
migrate_works/migrate_works_shell.py
util_lib/AOLogger.py
util_lib/GetFromBUDA.py
util_lib/__init__.py
util_lib/utils.py
util_lib/version.py
bdrc_util-1.0.14.dist-info/LICENSE
bdrc_util-1.0.14.dist-info/METADATA
bdrc_util-1.0.14.dist-info/WHEEL
bdrc_util-1.0.14.dist-info/entry_points.txt
bdrc_util-1.0.14.dist-info/top_level.txt
bdrc_util-1.0.14.dist-info/RECORD
