Metadata-Version: 2.2
Name: bdrc-util
Version: 1.0.14
Summary: BDRC Utilities
Author-email: jimk <jimk@bdrc.io>
License: MIT License
Project-URL: Homepage, https://github.com/buda-base/archive-ops/tree/master/bdrc-util
Classifier: Programming Language :: Python :: 3
Classifier: License :: OSI Approved :: MIT License
Classifier: Operating System :: OS Independent
Classifier: Intended Audience :: System Administrators
Classifier: Development Status :: 5 - Production/Stable
Requires-Python: >=3.9
License-File: LICENSE
Requires-Dist: bdrc-db-lib>=1.0.22
Requires-Dist: pandas
Requires-Dist: boto3
Requires-Dist: requests
Requires-Dist: cachetools
Requires-Dist: s3pathlib
Requires-Dist: bdrc-bag
